setup.py
psu364x/__init__.py
psu364x/base.py
psu364x.egg-info/PKG-INFO
psu364x.egg-info/SOURCES.txt
psu364x.egg-info/dependency_links.txt
psu364x.egg-info/requires.txt
psu364x.egg-info/top_level.txt