Metadata-Version: 1.0
Name: psu364x
Version: 0.1
Summary: Module for controlling Array 364X power supplies
Home-page: http://www.bfrigon.com/python-psu364x
Author: Benoit Frigon
Author-email: benoit@frigon.info
License: GPL
Platform: UNKNOWN
